Workbook

Sheet Analises
F2: % de Participação de cada Banco
F3: BMG | G3: 3665.45 | H3: =G3/$G$11 -> 0.0026068343 | J3: Rótulos de Linha | K3: Contagem de Nº CONTRATO
B4: contagem de contratos | C4: =COUNTA(fContratos[Nº CONTRATO]) -> 222 | F4: BRADESCO | G4: 268242.96 | H4: =G4/$G$11 -> 0.19077193 | J4: Operador | K4: Contagem de Nº CONTRATO | L4: Coluna1
B5: contagem de contratos aberbados | C5: =SUMIF(fContratos[AVERBADO],1,fContratos[AVERBADO]) -> 11 | F5: C6 BANK | G5: 6647.47 | H5: =G5/$G$11 -> 0.0047276195 | J5: CLAUDIO | K5: 1 | L5: =Tabela7[[#This Row],[Contagem de Nº CONTRATO]]/$K$12 -> 0.0045045045
B6: valor bruto | C6: =SUM(fContratos[VLR BRUTO]) -> 1406092.4 | F6: DAYCOVAL | G6: 23893.37 | H6: =G6/$G$11 -> 0.016992745 | J6: ANA JULIA | K6: 9 | L6: =Tabela7[[#This Row],[Contagem de Nº CONTRATO]]/$K$12 -> 0.040540541
B7: Ticket médio ( bruto / qtd contratos) | C7: =C6/C4 -> 6333.7497 | F7: ITAU BMG | G7: 3278.93 | H7: =G7/$G$11 -> 0.0023319448 | J7: PEDRO | K7: 13 | L7: =Tabela7[[#This Row],[Contagem de Nº CONTRATO]]/$K$12 -> 0.058558559
B8: prazo dos contratos(dias) | C8: =AVERAGE(fContratos[PRAZO]) -> 56.486486 | F8: OLÉ | G8: 2868.09 | H8: =G8/$G$11 -> 0.0020397592 | J8: ALEXANDRE | K8: 16 | L8: =Tabela7[[#This Row],[Contagem de Nº CONTRATO]]/$K$12 -> 0.072072072
B9: % contratos cancelados | C9: =COUNTIF(fContratos!K:K,"CANCELADO")/COUNTA(fContratos!K:K) -> 0.48430493 | F9: PAN | G9: 615576.4 | H9: =G9/$G$11 -> 0.43779227 | J9: DANIELE | K9: 24 | L9: =Tabela7[[#This Row],[Contagem de Nº CONTRATO]]/$K$12 -> 0.10810811
B10: % Converção | C10: =COUNTIF(fContratos!Y:Y,1)/COUNTA(fContratos!A:A) -> 0.049327354 | F10: SAFRA | G10: 481919.76 | H10: =G10/$G$11 -> 0.3427369 | J10: AMANDA | K10: 61 | L10: =Tabela7[[#This Row],[Contagem de Nº CONTRATO]]/$K$12 -> 0.27477477
B11: Volume Bruto averbado | C11: =SUMIF(fContratos!Y:Y,1,fContratos!R:R) -> 57137.08 | F11: Total Geral | G11: 1406092.4 | H11: =SUM(H3:H10) -> 1 | J11: MARIA | K11: 98 | L11: =Tabela7[[#This Row],[Contagem de Nº CONTRATO]]/$K$12 -> 0.44144144
J12: Total Geral | K12: 222 | L12: =Tabela7[[#This Row],[Contagem de Nº CONTRATO]]/$K$12 -> 1
B19: CONTAGEM DE CONTRATO POR OPERADOR | E19: Valor Bruto por Banco
B20: Rótulos de Linha | C20: Contagem de Nº CONTRATO | E20: Rótulos de Linha | F20: Soma de VLR BRUTO | H20: Rótulos de Linha | I20: Contagem de Nº CONTRATO
B21: MARIA | C21: 98 | E21: BMG | F21: 3665.45 | H21: CANCELADO | I21: 108
B22: AMANDA | C22: 61 | E22: BRADESCO | F22: 268242.96 | H22: AG. ASS. DIG | I22: 48
B23: DANIELE | C23: 24 | E23: C6 BANK | F23: 6647.47 | H23: EM ANÁLISE | I23: 19
B24: ALEXANDRE | C24: 16 | E24: DAYCOVAL | F24: 23893.37 | H24: EM NEGOCIAÇÃO | I24: 10
B25: PEDRO | C25: 13 | E25: ITAU BMG | F25: 3278.93 | H25: PENDENTE | I25: 10
B26: ANA JULIA | C26: 9 | E26: OLÉ | F26: 2868.09 | H26: AVERBADO | I26: 8
B27: CLAUDIO | C27: 1 | E27: PAN | F27: 615576.4 | H27: AGUARD. CIP | I27: 8
B28: Total Geral | C28: 222 | E28: SAFRA | F28: 481919.76 | H28: DIGITAR | I28: 8
E29: Total Geral | F29: 1406092.4 | H29: SALDO PAGO | I29: 3
H30: Total Geral | I30: 222
B57: Rótulos de Linha | C57: Faixa Prazo | D57: Contagem de Nº CONTRATO | E57: Soma de VLR BRUTO
B58: ALEXANDRE | C58: <24 | D58: 4 | E58: 40250
C59: 25-60 | D59: 2 | E59: 36284.38
C60: 61-84 | D60: 10 | E60: 115890.35
B61: AMANDA | C61: <24 | D61: 13 | E61: 77052.21
C62: 25-60 | D62: 19 | E62: 199362.06
C63: 61-84 | D63: 29 | E63: 121041.2
B64: ANA JULIA | C64: <24 | D64: 2 | E64: 23700
C65: >84 | D65: 1 | E65: 0
C66: 25-60 | D66: 4 | E66: 78950.37 | G66: Rótulos de Linha | H66: Soma de VLR BRUTO
C67: 61-84 | D67: 2 | E67: 0 | G67: abril | H67: 165522.51
B68: CLAUDIO | C68: <24 | D68: 1 | E68: 15000 | G68: agosto | H68: 97435.21
B69: DANIELE | C69: <24 | D69: 3 | E69: 29538.52 | G69: dezembro | H69: 186254.76
C70: 25-60 | D70: 8 | E70: 67447.52 | G70: fevereiro | H70: 147661.59
C71: 61-84 | D71: 13 | E71: 35724.98 | G71: janeiro | H71: 169027.02
B72: MARIA | C72: <24 | D72: 22 | E72: 28626.47 | G72: julho | H72: 76209.21
C73: >84 | D73: 4 | E73: 35405.81 | G73: junho | H73: 108456.02
C74: 25-60 | D74: 15 | E74: 135854.75 | G74: maio | H74: 129219.51
C75: 61-84 | D75: 57 | E75: 208433.18 | G75: março | H75: 85774.23
B76: PEDRO | C76: <24 | D76: 1 | E76: 6500 | G76: novembro | H76: 64949.89
C77: 25-60 | D77: 6 | E77: 94795.46 | G77: outubro | H77: 121571.09
C78: 61-84 | D78: 6 | E78: 56235.17 | G78: setembro | H78: 54011.39
B79: Total Geral | D79: 222 | E79: 1406092.4 | G79: Total Geral | H79: 1406092.4
B90: Rótulos de Linha | C90: Contagem de Nº CONTRATO | E90: Rótulos de Linha | F90: Soma de VLR BRUTO
B91: abril | C91: 18 | E91: BMG | F91: 3665.45
B92: agosto | C92: 18 | E92: BRADESCO | F92: 268242.96
B93: dezembro | C93: 18 | E93: C6 BANK | F93: 6647.47
B94: fevereiro | C94: 18 | E94: DAYCOVAL | F94: 23893.37
B95: janeiro | C95: 19 | E95: ITAU BMG | F95: 3278.93
B96: julho | C96: 19 | E96: OLÉ | F96: 2868.09
B97: junho | C97: 18 | E97: PAN | F97: 615576.4
B98: maio | C98: 19 | E98: SAFRA | F98: 481919.76
B99: março | C99: 19 | E99: Total Geral | F99: 1406092.4
B100: novembro | C100: 19
B101: outubro | C101: 18
B102: setembro | C102: 19
B103: Total Geral | C103: 222

Sheet Dashboard

Sheet Insights
B2: INSIGHTS DA OPERAÇÃO DE CRÉDITO CONSIGNADO
B5: VISÃO GERAL
B6: Indicador | C6: Valor | D6: Leitura
B7: Total de contratos digitados | C7: =COUNTA(fContratos[Nº CONTRATO]) -> 222 | D7: Volume operacional do período
B8: Contratos averbados (pagos) | C8: =COUNTIFS(fContratos[AVERBADO],1) -> 11 | D8: Contratos que efetivamente geraram receita
B9: Taxa de conversão | C9: =C8/C7 -> 0.04954955 | D9: % de contratos digitados que viraram receita
B10: Volume bruto digitado (R$) | C10: =SUM(fContratos[VLR BRUTO]) -> 1406092.4 | D10: Total movimentado em propostas
B11: Volume bruto averbado (R$) | C11: =SUMIFS(fContratos[VLR BRUTO],fContratos[AVERBADO],1) -> 57137.08 | D11: Receita efetiva da carteira
B12: Ticket médio bruto | C12: =C10/C7 -> 6333.7497 | D12: Valor médio por contrato digitado
B13: Taxa de cancelamento | C13: =COUNTIF(fContratos[STATUS],"CANCELADO")/COUNTA(fContratos[STATUS]) -> 0.48648649 | D13: % de propostas que foram canceladas
B14: Prazo médio (parcelas) | C14: =AVERAGE(fContratos[PRAZO]) -> 56.486486 | D14: Quantidade média de parcelas contratadas
B16: ALERTAS CRÍTICOS
B17: Achado | C17: Métrica | D17: Recomendação
B18: Cancelamento ALTO | C18: =COUNTIF(fContratos[STATUS],"CANCELADO")/COUNTA(fContratos[STATUS]) -> 0.48648649 | D18: Quase metade dos contratos cancela — investigar causas (análise de crédito, qualidade do lead, scripts)
B19: Conversão BAIXA (averbado/digitado) | C19: =C8/C7 -> 0.04954955 | D19: Apenas ~5% dos contratos viram receita — gargalo no funil de averbação
B20: Concentração em 2 bancos (PAN + SAFRA) | C20: =(SUMIFS(fContratos[VLR BRUTO],fContratos[[BANCO ]],"PAN")+SUMIFS(fContratos[VLR BRUTO],fContratos[[BANCO ]],"SAFRA"))/SUM(fContratos[VLR BRUTO]) -> 0.78052917 | D20: Risco de dependência — diversificar parcerias bancárias
B21: Status 'AG. ASS. DIG' parados | C21: =COUNTIF(fContratos[STATUS],"AG. ASS. DIG") -> 48 | D21: Contratos aguardando assinatura digital — acionar clientes para finalizar
B22: Volume perdido por cancelamento (R$) | C22: =SUMIFS(fContratos[VLR BRUTO],fContratos[STATUS],"CANCELADO") -> 453382.24 | D22: Valor que entrou no funil mas não virou receita
B24: DESTAQUES POR OPERADOR
B25: Indicador | C25: Valor | D25: Comentário
B26: Operador com mais contratos | C26: =INDEX(Analises!B21:B27,MATCH(MAX(Analises!C21:C27),Analises!C21:C27,0)) -> MARIA | D26: ="Lidera com "&MAX(Analises!C21:C27)&" contratos digitados" -> Lidera com 98 contratos digitados
B27: Operador com menos contratos | C27: =INDEX(Analises!B21:B27,MATCH(MIN(Analises!C21:C27),Analises!C21:C27,0)) -> CLAUDIO | D27: ="Apenas "&MIN(Analises!C21:C27)&" contrato(s) — avaliar performance ou realocar" -> Apenas 1 contrato(s) — avaliar performance ou realocar
B28: Top 2 operadores (% da carteira) | C28: =(LARGE(Analises!C21:C27,1)+LARGE(Analises!C21:C27,2))/SUM(Analises!C21:C27) -> 0.71621622 | D28: Concentração de produção em poucos operadores
B30: DESTAQUES POR BANCO
B31: Indicador | C31: Valor | D31: Comentário
B32: Banco líder em volume bruto | C32: =INDEX(Analises!E21:E28,MATCH(MAX(Analises!F21:F28),Analises!F21:F28,0)) -> PAN | D32: ="R$ "&TEXT(MAX(Analises!F21:F28),"#,##0.00")&" — principal parceiro" -> R$ 615576,4000 — principal parceiro
B33: Banco com menor volume | C33: =INDEX(Analises!E21:E28,MATCH(MIN(Analises!F21:F28),Analises!F21:F28,0)) -> OLÉ | D33: ="R$ "&TEXT(MIN(Analises!F21:F28),"#,##0.00")&" — oportunidade ou parceria a revisar" -> R$ 2868,09000 — oportunidade ou parceria a revisar
B34: % top banco no total | C34: =MAX(Analises!F21:F28)/SUM(Analises!F21:F28) -> 0.43779227 | D34: Concentração em um único banco
B36: SAZONALIDADE
B37: Indicador | C37: Valor | D37: Comentário
B38: Mês com mais contratos | C38: {=INDEX({"Jan";"Fev";"Mar";"Abr";"Mai";"Jun";"Jul";"Ago";"Set";"Out";"Nov";"Dez"},MATCH(MAX(COUNTIFS(fContratos[Mês],{1;2;3;4;5;6;7;8;9;10;11;12})),COUNTIFS(fContratos[Mês],{1;2;3;4;5;6;7;8;9;10;11;12}),0))} -> Jan | D38: Mês de pico operacional
B39: Mês com menos contratos | C39: {=INDEX({"Jan";"Fev";"Mar";"Abr";"Mai";"Jun";"Jul";"Ago";"Set";"Out";"Nov";"Dez"},MATCH(MIN(COUNTIFS(fContratos[Mês],{1;2;3;4;5;6;7;8;9;10;11;12})),COUNTIFS(fContratos[Mês],{1;2;3;4;5;6;7;8;9;10;11;12}),0))} -> Fev | D39: Mês para reforçar campanhas e prospecção
B40: Média mensal de contratos | C40: =C7/12 -> 18.5 | D40: Volume médio digitado por mês
B42: PLANO DE AÇÃO SUGERIDO
B43: Prioridade | C43: Ação | D43: Impacto esperado
B44: ALTA | C44: Investigar causas dos cancelamentos (48% da carteira) | D44: Reduzir perda de ~R$ 453 mil em volume
B45: ALTA | C45: Acionar contratos parados em AG. ASS. DIG | D45: Acelerar averbação e melhorar conversão
B46: MÉDIA | C46: Diversificar mix de bancos (78% em PAN+SAFRA) | D46: Reduzir risco de concentração
B47: MÉDIA | C47: Replicar práticas da MARIA (44% da produção) para demais | D47: Elevar produtividade média da equipe
B48: BAIXA | C48: Reforçar campanhas nos meses de menor produção | D48: Suavizar sazonalidade
B49: BAIXA | C49: Avaliar performance do operador CLAUDIO (1 contrato) | D49: Realocar ou treinar

Sheet fContratos
A1: DATA LANC. | B1: RETORNO CIP | C1: OPERADOR | D1: TIPO DE BENEFICIO | E1: CPF | F1: NOME | G1: Nº CONTRATO | H1: TIPO CONT. | I1: BANCO | J1: USUÁRIO | K1: STATUS | L1: DT. ANÁLISE | M1: Status Detalhado | N1: PRAZO | O1: Faixa Prazo | P1: PARCELA REDUZIDA | Q1: PARCELA ORIGINAL | R1: VLR BRUTO | S1: SALDO DEV. | T1: VLR LÍQUIDO | U1: TABELA | V1: RENTABILIDADE | W1: TOTAL (R$) | X1: DT AVERB. | Y1: AVERBADO | Z1: Mês | AA1: Ano | AB1: Ano_Mes | AC1: Tipo Simples
A2: 45658 | C2: AMANDA | D2: INSS | E2: 889.757.507-77 | F2: JOSÉ DA SILVA SANTOS | G2: SF-100001 | H2: NOVO (REDUÇÃO) | I2: SAFRA | K2: CANCELADO | L2: 45661 | N2: 84 | O2: 61-84 | P2: 0 | Q2: 94.5 | R2: 3923.89 | S2: 0 | T2: 0 | W2: 0 | Y2: 0 | Z2: 1 | AA2: 2025 | AB2: 2025-01 | AC2: NOVO
A3: 45659 | C3: AMANDA | D3: INSS | E3: 379.981.168-14 | F3: MARIA APARECIDA OLIVEIRA | G3: SF-100002 | H3: REFIN (REDUÇÃO) | I3: SAFRA | K3: CANCELADO | L3: 45662 | N3: 84 | O3: 61-84 | P3: 230.93 | Q3: 313.75 | R3: 11293.05 | S3: 11193.05 | T3: 100 | W3: 0 | Y3: 0 | Z3: 1 | AA3: 2025 | AB3: 2025-01 | AC3: REFIN
A4: 45661 | C4: PEDRO | D4: INSS | E4: 463.115.167-03 | F4: ROSA MARIA CARDOSO | G4: SF-100003 | H4: PORT (REDUÇÃO) | I4: SAFRA | K4: AG. ASS. DIG | L4: 45664 | N4: 21 | O4: <24 | P4: 350 | Q4: 375.7 | R4: 6500 | S4: 0 | T4: 6500 | W4: 0 | Y4: 0 | Z4: 1 | AA4: 2025 | AB4: 2025-01 | AC4: PORT
A5: 45663 | C5: ALEXANDRE | D5: INSS | E5: 360.047.834-19 | F5: JOÃO BATISTA FERREIRA | G5: SF-100005 | H5: REFIN (REDUÇÃO) | I5: SAFRA | K5: CANCELADO | L5: 45666 | N5: 84 | O5: 61-84 | P5: 316.58 | Q5: 371.46 | R5: 14815.31 | S5: 0 | T5: 14815.31 | W5: 0 | Y5: 0 | Z5: 1 | AA5: 2025 | AB5: 2025-01 | AC5: REFIN
A6: 45664 | C6: MARIA | D6: INSS | E6: 635.575.794-63 | F6: ANA LÚCIA RODRIGUES | G6: SF-100006 | H6: PORT (REDUÇÃO) | I6: SAFRA | K6: AG. ASS. DIG | L6: 45667 | N6: 62 | O6: 61-84 | P6: 158 | Q6: 173.43 | R6: 7100 | S6: 0 | T6: 7100 | W6: 0 | Y6: 0 | Z6: 1 | AA6: 2025 | AB6: 2025-01 | AC6: PORT
A7: 45666 | C7: ANA JULIA | D7: INSS | E7: 651.400.432-90 | F7: LUIZ CARLOS ALMEIDA | G7: SF-100007 | H7: PORT (REDUÇÃO) | I7: SAFRA | K7: AG. ASS. DIG | L7: 45669 | N7: 0 | O7: <24 | P7: 520 | Q7: 579.07 | R7: 14700 | S7: 0 | T7: 14700 | W7: 0 | Y7: 0 | Z7: 1 | AA7: 2025 | AB7: 2025-01 | AC7: PORT
A8: 45668 | C8: ALEXANDRE | D8: INSS | E8: 335.511.472-45 | F8: CLAUDETE FERNANDES COSTA | G8: SF-100008 | H8: REFIN (JUN + RED) | I8: SAFRA | K8: CANCELADO | L8: 45671 | N8: 84 | O8: 61-84 | P8: 0 | Q8: 299.74 | R8: 15296.75 | S8: 14996.75 | T8: 300 | W8: 0 | Y8: 0 | Z8: 1 | AA8: 2025 | AB8: 2025-01 | AC8: REFIN
A9: 45669 | C9: DANIELE | D9: INSS | E9: 488.012.471-10 | F9: PAULO ROBERTO MARTINS | G9: SF-100009 | H9: PORT (REDUÇÃO) | I9: SAFRA | K9: CANCELADO | L9: 45672 | N9: 0 | O9: <24 | P9: 175 | Q9: 200 | R9: 6600 | S9: 0 | T9: 6600 | W9: 0 | Y9: 0 | Z9: 1 | AA9: 2025 | AB9: 2025-01 | AC9: PORT
A10: 45671 | C10: ANA JULIA | D10: INSS | E10: 845.895.485-26 | F10: TEREZINHA DE JESUS RIBEIRO | G10: SF-100010 | H10: PORT (REDUÇÃO) | I10: SAFRA | K10: CANCELADO | L10: 45674 | N10: 0 | O10: <24 | P10: 265 | Q10: 303.41 | R10: 9000 | S10: 0 | T10: 9000 | W10: 0 | Y10: 0 | Z10: 1 | AA10: 2025 | AB10: 2025-01 | AC10: PORT
A11: 45673 | C11: ANA JULIA | D11: INSS | E11: 958.177.537-57 | F11: CARLOS EDUARDO BARBOSA | G11: SF-100011 | H11: REFIN DE PORT (REDUÇÃO) | I11: SAFRA | K11: AG. ASS. DIG | L11: 45676 | N11: 84 | O11: 61-84 | P11: 758.01 | Q11: 792.96 | R11: 0 | S11: 0 | T11: 0 | W11: 0 | Y11: 0 | Z11: 1 | AA11: 2025 | AB11: 2025-01 | AC11: REFIN DE PORT
A12: 45674 | C12: ANA JULIA | D12: INSS | E12: 775.282.586-12 | F12: CONCEIÇÃO APARECIDA DIAS | G12: SF-100012 | H12: PORT (REDUÇÃO) | I12: SAFRA | K12: AG. ASS. DIG | L12: 45677 | N12: 59 | O12: 25-60 | P12: 758.01 | Q12: 792.96 | R12: 31502.18 | S12: 0 | T12: 31502.18 | W12: 0 | Y12: 0 | Z12: 1 | AA12: 2025 | AB12: 2025-01 | AC12: PORT
A13: 45676 | C13: MARIA | D13: INSS | E13: 328.804.696-12 | F13: MANOEL FRANCISCO GOMES | G13: SF-100013 | H13: REFIN DE PORT (REDUÇÃO) | I13: SAFRA | K13: AG. ASS. DIG | L13: 45679 | N13: 84 | O13: 61-84 | P13: 170.28 | Q13: 274.55 | R13: 0 | S13: 8495.84 | T13: -8495.84 | W13: 0 | Y13: 0 | Z13: 1 | AA13: 2025 | AB13: 2025-01 | AC13: REFIN DE PORT
... A25: 45695 | C25: ALEXANDRE | D25: INSS | E25: 471.232.622-00 | F25: GERALDO MAGELA TEIXEIRA | G25: PN-100009 | H25: PORT (REDUÇÃO) | I25: BRADESCO | K25: DIGITAR | L25: 45698 | N25: 54 | O25: 25-60 | P25: 536.92 | Q25: 646.72 | R25: 0 | S25: 0 | T25: 0 | W25: 0 | Y25: 0 | Z25: 2 | AA25: 2025 | AB25: 2025-02 | AC25: PORT
A26: 45697 | B26: 45704 | C26: MARIA | D26: INSS | E26: 811.025.517-81 | F26: HÉLIO PEREIRA DA CRUZ | G26: PN-100011 | H26: REFIN DE PORT (REDUÇÃO) | I26: PAN | K26: AVERBADO | L26: 45700 | N26: 84 | O26: 61-84 | P26: 69.94 | Q26: 84.13 | R26: 3515.42 | S26: 3086.47 | T26: 428.95 | W26: 0 | X26: 45707 | Y26: 1 | Z26: 2 | AA26: 2025 | AB26: 2025-02 | AC26: REFIN DE PORT
A27: 45698 | B27: 45705 | C27: MARIA | D27: INSS | E27: 836.292.520-15 | F27: DIRCE MARIA CAMPOS | G27: SF-100016 | H27: REFIN DE PORT (REDUÇÃO) | I27: PAN | K27: AVERBADO | L27: 45701 | N27: 84 | O27: 61-84 | P27: 50.84 | Q27: 56.42 | R27: 2207.97 | S27: 1411.23 | T27: 796.74 | W27: 0 | X27: 45708 | Y27: 1 | Z27: 2 | AA27: 2025 | AB27: 2025-02 | AC27: REFIN DE PORT
A28: 45700 | B28: 45707 | C28: MARIA | D28: INSS | E28: 089.554.706-08 | F28: ALCIDES FERREIRA NETO | G28: PN-100012 | H28: REFIN DE PORT (REDUÇÃO) | I28: PAN | K28: AVERBADO | L28: 45703 | N28: 84 | O28: 61-84 | P28: 50.22 | Q28: 59.64 | R28: 2311.44 | S28: 1928.78 | T28: 382.66 | W28: 0 | X28: 45710 | Y28: 1 | Z28: 2 | AA28: 2025 | AB28: 2025-02 | AC28: REFIN DE PORT
A29: 45701 | C29: AMANDA | D29: INSS | E29: 736.526.833-90 | F29: BENEDITO CARLOS ARAÚJO | G29: PN-100014 | H29: PORT (REDUÇÃO) | I29: SAFRA | K29: CANCELADO | L29: 45704 | N29: 41 | O29: 25-60 | P29: 628.22 | Q29: 734.41 | R29: 20500 | S29: 0 | T29: 20500 | W29: 0 | Y29: 0 | Z29: 2 | AA29: 2025 | AB29: 2025-02 | AC29: PORT
A30: 45703 | B30: 45710 | C30: PEDRO | D30: INSS | E30: 591.568.765-43 | F30: IVONE DA CONCEIÇÃO MELO | G30: BM-100001 | H30: REFIN DE PORT (REDUÇÃO) | I30: PAN | K30: CANCELADO | L30: 45706 | N30: 84 | O30: 61-84 | P30: 249.12 | Q30: 373.6 | R30: 0 | S30: 0 | T30: 0 | W30: 0 | Y30: 0 | Z30: 2 | AA30: 2025 | AB30: 2025-02 | AC30: REFIN DE PORT
A31: 45704 | B31: 45711 | C31: PEDRO | D31: INSS | E31: 373.297.437-52 | F31: CÉLIA REGINA CAVALCANTE | G31: PN-100016 | H31: PORT (REDUÇÃO) | I31: PAN | K31: CANCELADO | L31: 45707 | N31: 56 | O31: 25-60 | P31: 249.12 | Q31: 373.6 | R31: 10000 | S31: 0 | T31: 10000 | W31: 0 | Y31: 0 | Z31: 2 | AA31: 2025 | AB31: 2025-02 | AC31: PORT
A32: 45706 | B32: 45713 | C32: MARIA | D32: INSS | E32: 872.356.738-46 | F32: ANTÔNIO MARCOS RAMOS | G32: IT-100001 | H32: REFIN DE PORT (REDUÇÃO) | I32: PAN | K32: CANCELADO | L32: 45709 | N32: 84 | O32: 61-84 | P32: 832.76 | Q32: 1000 | R32: 0 | S32: 0 | T32: 0 | W32: 0 | Y32: 0 | Z32: 2 | AA32: 2025 | AB32: 2025-02 | AC32: REFIN DE PORT
A33: 45707 | B33: 45714 | C33: MARIA | D33: INSS | E33: 298.342.563-27 | F33: MARIA DAS GRAÇAS LEAL | G33: IT-100002 | H33: PORT (REDUÇÃO) | I33: PAN | K33: CANCELADO | L33: 45710 | N33: 60 | O33: 61-84 | P33: 983.52 | Q33: 1000 | R33: 41800 | S33: 0 | T33: 41800 | W33: 0 | Y33: 0 | Z33: 2 | AA33: 2025 | AB33: 2025-02 | AC33: PORT
A34: 45709 | C34: MARIA | D34: INSS | E34: 582.384.950-03 | F34: ORLANDO BATISTA NOGUEIRA | G34: PN-100017 | H34: SAQUE COMP. | I34: BMG | K34: PENDENTE | L34: 45712 | N34: 0 | O34: <24 | P34: 0 | Q34: 0 | R34: 217.11 | S34: 0 | T34: 217.11 | W34: 0 | Y34: 0 | Z34: 2 | AA34: 2025 | AB34: 2025-02 | AC34: SAQUE COMP.
A35: 45710 | B35: 45717 | C35: MARIA | D35: INSS | E35: 187.382.040-51 | F35: VERA LÚCIA MONTEIRO | G35: PN-100018 | H35: PORT (REDUÇÃO) | I35: PAN | K35: CANCELADO | L35: 45713 | N35: 72 | O35: 61-84 | P35: 60.09 | Q35: 95.37 | R35: 2850 | S35: 0 | T35: 2850 | W35: 0 | Y35: 0 | Z35: 2 | AA35: 2025 | AB35: 2025-02 | AC35: PORT
A36: 45712 | C36: MARIA | D36: INSS | E36: 742.601.274-99 | F36: WALTER LUIZ DE PAULA | G36: PN-100019 | H36: REFIN (REDUÇÃO) | I36: ITAU BMG | K36: AG. ASS. DIG | L36: 45715 | N36: 84 | O36: 61-84 | P36: 0 | Q36: 37.61 | R36: 1568.39 | S36: 1260.81 | T36: 307.58 | W36: 0 | Y36: 0 | Z36: 2 | AA36: 2025 | AB36: 2025-02 | AC36: REFIN
A37: 45713 | C37: MARIA | D37: INSS | E37: 983.669.381-38 | F37: NAIR DOS SANTOS BORGES | G37: PN-100020 | H37: REFIN (REDUÇÃO) | I37: ITAU BMG | K37: AG. ASS. DIG | L37: 45716 | N37: 84 | O37: 61-84 | P37: 0 | Q37: 35.22 | R37: 1710.54 | S37: 1431.93 | T37: 278.61 | W37: 0 | Y37: 0 | Z37: 2 | AA37: 2025 | AB37: 2025-02 | AC37: REFIN
A38: 45715 | B38: 45722 | C38: AMANDA | D38: INSS | E38: 920.289.568-31 | F38: EDUARDO SANTANA FILHO | G38: PN-100021 | H38: PORT (REDUÇÃO) | I38: PAN | K38: CANCELADO | L38: 45718 | N38: 57 | O38: 25-60 | P38: 196.77 | Q38: 299.3 | R38: 8000 | S38: 0 | T38: 8000 | W38: 0 | Y38: 0 | Z38: 2 | AA38: 2025 | AB38: 2025-02 | AC38: PORT
A39: 45717 | C39: AMANDA | D39: INSS | E39: 105.304.772-76 | F39: HELENA MARIA BARROS | G39: PN-100022 | H39: NOVO (REDUÇÃO) | I39: PAN | K39: CANCELADO | L39: 45720 | N39: 84 | O39: 61-84 | P39: 0 | Q39: 73.46 | R39: 3016.62 | S39: 0 | T39: 3016.62 | W39: 0 | Y39: 0 | Z39: 3 | AA39: 2025 | AB39: 2025-03 | AC39: NOVO
A40: 45718 | C40: AMANDA | D40: INSS | E40: 290.954.711-19 | F40: RICARDO PEREIRA GONÇALVES | G40: PN-100023 | H40: NOVO (REDUÇÃO) | I40: PAN | K40: CANCELADO | L40: 45721 | N40: 84 | O40: 61-84 | P40: 0 | Q40: 88.73 | R40: 3642.44 | S40: 0 | T40: 3642.44 | W40: 0 | Y40: 0 | Z40: 3 | AA40: 2025 | AB40: 2025-03 | AC40: NOVO
A41: 45720 | C41: MARIA | D41: INSS | E41: 328.804.696-12 | F41: MANOEL FRANCISCO GOMES | G41: PN-100024 | H41: REFIN DE PORT (REDUÇÃO) | I41: PAN | K41: CANCELADO | L41: 45723 | N41: 84 | O41: 61-84 | P41: 285 | Q41: 0 | R41: 0 | S41: 0 | T41: 0 | W41: 0 | Y41: 0 | Z41: 3 | AA41: 2025 | AB41: 2025-03 | AC41: REFIN DE PORT
A42: 45722 | C42: MARIA | D42: INSS | E42: 134.926.533-42 | F42: MÁRIO ROBERTO MAGALHÃES | G42: PN-100025 | H42: PORT (REDUÇÃO) | I42: PAN | K42: CANCELADO | L42: 45725 | N42: 57 | O42: 25-60 | P42: 344.35 | Q42: 0 | R42: 14000 | S42: 0 | T42: 14000 | W42: 0 | Y42: 0 | Z42: 3 | AA42: 2025 | AB42: 2025-03 | AC42: PORT
A43: 45723 | C43: MARIA | D43: INSS | E43: 992.757.262-97 | F43: CLEUSA MARIA DA SILVA | G43: SF-100017 | H43: NOVO (REDUÇÃO) | I43: PAN | K43: CANCELADO | L43: 45726 | N43: 0 | O43: <24 | P43: 0 | Q43: 74.85 | R43: 0 | S43: 0 | T43: 0 | W43: 0 | Y43: 0 | Z43: 3 | AA43: 2025 | AB43: 2025-03 | AC43: NOVO
A44: 45725 | C44: MARIA | D44: INSS | E44: 100.811.864-38 | F44: NIVALDO DE SOUZA REIS | G44: SF-100018 | H44: NOVO (REDUÇÃO) | I44: PAN | K44: CANCELADO | L44: 45728 | N44: 0 | O44: <24 | P44: 0 | Q44: 33.32 | R44: 0 | S44: 0 | T44: 0 | W44: 0 | Y44: 0 | Z44: 3 | AA44: 2025 | AB44: 2025-03 | AC44: NOVO
A45: 45727 | C45: MARIA | D45: INSS | E45: 293.103.404-43 | F45: DALVA MARIA TORRES | G45: PN-100026 | H45: REFIN DE PORT (REDUÇÃO) | I45: PAN | K45: CANCELADO | L45: 45730 | N45: 0 | O45: <24 | P45: 178 | Q45: 286.2 | R45: 0 | S45: 0 | T45: 0 | W45: 0 | Y45: 0 | Z45: 3 | AA45: 2025 | AB45: 2025-03 | AC45: REFIN DE PORT
A46: 45728 | C46: MARIA | D46: INSS | E46: 239.742.164-93 | F46: MARLENE DE FÁTIMA PINTO | G46: PN-100027 | H46: PORT (REDUÇÃO) | I46: PAN | K46: CANCELADO | L46: 45731 | N46: 0 | O46: <24 | P46: 252.88 | Q46: 286.2 | R46: 0 | S46: 0 | T46: 0 | W46: 0 | Y46: 0 | Z46: 3 | AA46: 2025 | AB46: 2025-03 | AC46: PORT
A47: 45730 | C47: DANIELE | D47: INSS | E47: 770.868.654-78 | F47: MERCEDES APARECIDA DUARTE | G47: BM-100002 | H47: PORT (REDUÇÃO) | I47: SAFRA | K47: PENDENTE | L47: 45733 | N47: 60 | O47: 61-84 | P47: 249.33 | Q47: 313 | R47: 10850 | S47: 0 | T47: 10850 | W47: 0 | Y47: 0 | Z47: 3 | AA47: 2025 | AB47: 2025-03 | AC47: PORT
A48: 45732 | B48: 45739 | C48: DANIELE | D48: INSS | E48: 148.421.749-55 | F48: JOSÉ DA SILVA SANTOS | G48: SF-100019 | H48: PORT (REDUÇÃO) | I48: SAFRA | K48: CANCELADO | L48: 45735 | N48: 0 | O48: <24 | P48: 415.87 | Q48: 494.7 | R48: 17000 | S48: 0 | T48: 17000 | W48: 0 | Y48: 0 | Z48: 3 | AA48: 2025 | AB48: 2025-03 | AC48: PORT
A49: 45733 | B49: 45740 | C49: ANA JULIA | D49: INSS | E49: 809.180.333-79 | F49: MARIA APARECIDA OLIVEIRA | G49: SF-100020 | H49: REFIN DE PORT (REDUÇÃO) | I49: PAN | K49: CANCELADO | L49: 45736 | N49: 84 | O49: >84 | P49: 700 | Q49: 993.81 | R49: 0 | S49: 0 | T49: 0 | W49: 0 | Y49: 0 | Z49: 3 | AA49: 2025 | AB49: 2025-03 | AC49: REFIN DE PORT
A50: 45735 | B50: 45742 | C50: ANA JULIA | D50: INSS | E50: 591.568.765-43 | F50: IVONE DA CONCEIÇÃO MELO | G50: BM-100003 | H50: PORT (REDUÇÃO) | I50: PAN | K50: CANCELADO | L50: 45738 | N50: 58 | O50: 25-60 | P50: 844.71 | Q50: 993.81 | R50: 34800 | S50: 0 | T50: 34800 | W50: 0 | Y50: 0 | Z50: 3 | AA50: 2025 | AB50: 2025-03 | AC50: PORT
A51: 45737 | C51: MARIA | D51: INSS | E51: 237.515.206-04 | F51: FRANCISCA DE SOUZA LIMA | G51: BR-100002 | H51: SAQUE COMP. | I51: BMG | K51: AVERBADO | L51: 45740 | N51: 0 | O51: <24 | P51: 0 | Q51: 0 | R51: 705.17 | S51: 0 | T51: 705.17 | W51: 0 | X51: 45747 | Y51: 1 | Z51: 3 | AA51: 2025 | AB51: 2025-03 | AC51: SAQUE COMP.
A52: 45738 | C52: MARIA | D52: INSS | E52: 226.932.065-05 | F52: JOÃO BATISTA FERREIRA | G52: BR-100003 | H52: REFIN DE PORT (REDUÇÃO) | I52: SAFRA | K52: CANCELADO | L52: 45741 | N52: 84 | O52: 61-84 | P52: 0 | Q52: 286.2 | R52: 0 | S52: 0 | T52: 0 | W52: 0 | Y52: 0 | Z52: 3 | AA52: 2025 | AB52: 2025-03 | AC52: REFIN DE PORT
A53: 45740 | C53: MARIA | D53: INSS | E53: 425.490.298-25 | F53: EDNA APARECIDA SOARES | G53: BR-100004 | H53: PORT (REDUÇÃO) | I53: SAFRA | K53: CANCELADO | L53: 45743 | N53: 44 | O53: 25-60 | P53: 246.88 | Q53: 286.2 | R53: 0 | S53: 0 | T53: 0 | W53: 0 | Y53: 0 | Z53: 3 | AA53: 2025 | AB53: 2025-03 | AC53: PORT
A54: 45742 | C54: MARIA | D54: INSS | E54: 323.862.559-76 | F54: LUIZ CARLOS ALMEIDA | G54: BR-100005 | H54: CARTÃO S/SAQUE | I54: BMG | K54: AVERBADO | L54: 45745 | N54: 0 | O54: <24 | P54: 0 | Q54: 0 | R54: 1760 | S54: 0 | T54: 0 | W54: 0 | X54: 45752 | Y54: 1 | Z54: 3 | AA54: 2025 | AB54: 2025-03 | AC54: CARTÃO S/SAQUE
A55: 45743 | C55: MARIA | D55: INSS | E55: 701.275.722-60 | F55: CLAUDETE FERNANDES COSTA | G55: BR-100006 | H55: REFIN DE PORT (REDUÇÃO) | I55: BRADESCO | K55: CANCELADO | L55: 45746 | N55: 84 | O55: 61-84 | P55: 0 | Q55: 29.25 | R55: 0 | S55: 0 | T55: 0 | W55: 0 | Y55: 0 | Z55: 3 | AA55: 2025 | AB55: 2025-03 | AC55: REFIN DE PORT
A56: 45745 | C56: MARIA | D56: INSS | E56: 644.149.229-30 | F56: PAULO ROBERTO MARTINS | G56: BR-100007 | H56: PORT (REDUÇÃO) | I56: BRADESCO | K56: CANCELADO | L56: 45748 | N56: 0 | O56: <24 | P56: 0 | Q56: 29.25 | R56: 0 | S56: 0 | T56: 0 | W56: 0 | Y56: 0 | Z56: 3 | AA56: 2025 | AB56: 2025-03 | AC56: PORT
A57: 45747 | C57: MARIA | D57: INSS | E57: 884.007.054-26 | F57: TEREZINHA DE JESUS RIBEIRO | G57: BR-100008 | H57: REFIN DE PORT (REDUÇÃO) | I57: BRADESCO | K57: CANCELADO | L57: 45750 | N57: 84 | O57: 61-84 | P57: 0 | Q57: 135.8 | R57: 0 | S57: 0 | T57: 0 | W57: 0 | Y57: 0 | Z57: 3 | AA57: 2025 | AB57: 2025-03 | AC57: REFIN DE PORT
A58: 45748 | C58: MARIA | D58: INSS | E58: 998.574.880-18 | F58: CARLOS EDUARDO BARBOSA | G58: BR-100009 | H58: PORT (REDUÇÃO) | I58: BRADESCO | K58: CANCELADO | L58: 45751 | N58: 0 | O58: <24 | P58: 0 | Q58: 135.8 | R58: 0 | S58: 0 | T58: 0 | W58: 0 | Y58: 0 | Z58: 4 | AA58: 2025 | AB58: 2025-04 | AC58: PORT
A59: 45750 | C59: MARIA | D59: INSS | E59: 880.349.039-38 | F59: ROSA MARIA CARDOSO | G59: SF-100021 | H59: REFIN DE PORT (REDUÇÃO) | I59: BRADESCO | K59: CANCELADO | L59: 45753 | N59: 84 | O59: 61-84 | P59: 0 | Q59: 75.74 | R59: 0 | S59: 0 | T59: 0 | W59: 0 | Y59: 0 | Z59: 4 | AA59: 2025 | AB59: 2025-04 | AC59: REFIN DE PORT
A60: 45752 | C60: MARIA | D60: INSS | E60: 355.717.458-91 | F60: MANOEL FRANCISCO GOMES | G60: SF-100022 | H60: PORT (REDUÇÃO) | I60: BRADESCO | K60: CANCELADO | L60: 45755 | N60: 0 | O60: <24 | P60: 0 | Q60: 75.74 | R60: 0 | S60: 0 | T60: 0 | W60: 0 | Y60: 0 | Z60: 4 | AA60: 2025 | AB60: 2025-04 | AC60: PORT
A61: 45753 | C61: MARIA | D61: INSS | E61: 354.687.005-16 | F61: CONCEIÇÃO APARECIDA DIAS | G61: PN-100028 | H61: REFIN DE PORT (REDUÇÃO) | I61: BRADESCO | K61: CANCELADO | L61: 45756 | N61: 84 | O61: 61-84 | P61: 0 | Q61: 111 | R61: 0 | S61: 0 | T61: 0 | W61: 0 | Y61: 0 | Z61: 4 | AA61: 2025 | AB61: 2025-04 | AC61: REFIN DE PORT
A62: 45755 | C62: MARIA | D62: INSS | E62: 120.177.811-68 | F62: SEBASTIÃO PEREIRA NUNES | G62: PN-100029 | H62: PORT (REDUÇÃO) | I62: BRADESCO | K62: CANCELADO | L62: 45758 | N62: 0 | O62: <24 | P62: 0 | Q62: 111 | R62: 0 | S62: 0 | T62: 0 | W62: 0 | Y62: 0 | Z62: 4 | AA62: 2025 | AB62: 2025-04 | AC62: PORT
A63: 45756 | B63: 45763 | C63: PEDRO | D63: INSS | E63: 501.536.316-56 | F63: DIRCE MARIA CAMPOS | G63: PN-100030 | H63: REFIN DE PORT (REDUÇÃO) | I63: SAFRA | K63: CANCELADO | L63: 45759 | N63: 84 | O63: 61-84 | P63: 744.55 | Q63: 924.27 | R63: 0 | S63: 0 | T63: 30750 | W63: 0 | Y63: 0 | Z63: 4 | AA63: 2025 | AB63: 2025-04 | AC63: REFIN DE PORT
A64: 45758 | B64: 45765 | C64: PEDRO | D64: INSS | E64: 239.742.164-93 | F64: MARLENE DE FÁTIMA PINTO | G64: PN-100031 | H64: PORT (REDUÇÃO) | I64: SAFRA | K64: CANCELADO | L64: 45761 | N64: 58 | O64: 25-60 | P64: 744.55 | Q64: 924.27 | R64: 0 | S64: 0 | T64: 30750 | W64: 0 | Y64: 0 | Z64: 4 | AA64: 2025 | AB64: 2025-04 | AC64: PORT
A65: 45760 | B65: 45767 | C65: AMANDA | D65: INSS | E65: 845.895.485-26 | F65: TEREZINHA DE JESUS RIBEIRO | G65: BR-100010 | H65: REFIN DE PORT (REDUÇÃO) | I65: PAN | K65: CANCELADO | L65: 45763 | N65: 0 | O65: <24 | P65: 0 | Q65: 459.96 | R65: 0 | S65: 0 | T65: 0 | W65: 0 | Y65: 0 | Z65: 4 | AA65: 2025 | AB65: 2025-04 | AC65: REFIN DE PORT
A66: 45761 | B66: 45768 | C66: AMANDA | D66: INSS | E66: 099.941.394-67 | F66: BENEDITO CARLOS ARAÚJO | G66: BR-100011 | H66: PORT (REDUÇÃO) | I66: PAN | K66: CANCELADO | L66: 45764 | N66: 0 | O66: <24 | P66: 0 | Q66: 459.96 | R66: 14000 | S66: 0 | T66: 14000 | W66: 0 | Y66: 0 | Z66: 4 | AA66: 2025 | AB66: 2025-04 | AC66: PORT
A67: 45763 | C67: AMANDA | D67: INSS | E67: 889.757.507-77 | F67: JOSÉ DA SILVA SANTOS | G67: PN-100032 | H67: NOVO (REDUÇÃO) | I67: PAN | K67: CANCELADO | L67: 45766 | N67: 0 | O67: <24 | P67: 0 | Q67: 53.8 | R67: 2216.07 | S67: 0 | T67: 2216.07 | W67: 0 | Y67: 0 | Z67: 4 | AA67: 2025 | AB67: 2025-04 | AC67: NOVO
A68: 45765 | C68: AMANDA | D68: INSS | E68: 983.669.381-38 | F68: NAIR DOS SANTOS BORGES | G68: PN-100033 | H68: NOVO (REDUÇÃO) | I68: PAN | K68: CANCELADO | L68: 45768 | N68: 0 | O68: <24 | P68: 0 | Q68: 67.2 | R68: 2768.03 | S68: 0 | T68: 2768.03 | W68: 0 | Y68: 0 | Z68: 4 | AA68: 2025 | AB68: 2025-04 | AC68: NOVO
A69: 45766 | B69: 45773 | C69: PEDRO | D69: INSS | E69: 275.588.948-80 | F69: NEUSA TEREZINHA CASTRO | G69: PN-100034 | H69: REFIN DE PORT (REDUÇÃO) | I69: BRADESCO | K69: EM ANÁLISE | L69: 45769 | N69: 84 | O69: 61-84 | P69: 731 | Q69: 924.27 | R69: 38550 | S69: 38300 | T69: 250 | W69: 0 | Y69: 0 | Z69: 4 | AA69: 2025 | AB69: 2025-04 | AC69: REFIN DE PORT
A70: 45768 | B70: 45775 | C70: PEDRO | D70: INSS | E70: 811.025.517-81 | F70: HÉLIO PEREIRA DA CRUZ | G70: PN-100035 | H70: PORT (REDUÇÃO) | I70: BRADESCO | K70: AGUARD. CIP | L70: 45771 | N70: 58 | O70: 25-60 | P70: 923.1 | Q70: 924.27 | R70: 38300 | S70: 0 | T70: 38300 | W70: 0 | Y70: 0 | Z70: 4 | AA70: 2025 | AB70: 2025-04 | AC70: PORT
A71: 45769 | B71: 45776 | C71: AMANDA | D71: INSS | E71: 663.359.599-65 | F71: EDNA APARECIDA SOARES | G71: PN-100036 | H71: REFIN DE PORT (REDUÇÃO) | I71: PAN | K71: EM ANÁLISE | L71: 45772 | N71: 84 | O71: 61-84 | P71: 330 | Q71: 459.96 | R71: 16487.64 | S71: 15816.67 | T71: 670.97 | W71: 0 | Y71: 0 | Z71: 4 | AA71: 2025 | AB71: 2025-04 | AC71: REFIN DE PORT
A72: 45771 | B72: 45778 | C72: AMANDA | D72: INSS | E72: 804.912.733-51 | F72: GERALDO MAGELA TEIXEIRA | G72: SF-100023 | H72: PORT (REDUÇÃO) | I72: PAN | K72: SALDO PAGO | L72: 45774 | N72: 55 | O72: 25-60 | P72: 411.17 | Q72: 459.96 | R72: 15816.67 | S72: 0 | T72: 15816.67 | W72: 0 | X72: 45781 | Y72: 1 | Z72: 4 | AA72: 2025 | AB72: 2025-04 | AC72: PORT
A73: 45773 | C73: AMANDA | D73: INSS | E73: 124.258.428-97 | F73: SEBASTIÃO PEREIRA NUNES | G73: SF-100024 | H73: REFIN DE PORT (REDUÇÃO) | I73: PAN | K73: AG. ASS. DIG | L73: 45776 | N73: 84 | O73: 61-84 | P73: 272 | Q73: 397.71 | R73: 13584.1 | S73: 13300 | T73: 284.1 | W73: 0 | Y73: 0 | Z73: 4 | AA73: 2025 | AB73: 2025-04 | AC73: REFIN DE PORT
A74: 45774 | C74: AMANDA | D74: INSS | E74: 247.098.969-29 | F74: HÉLIO PEREIRA DA CRUZ | G74: SF-100025 | H74: PORT (REDUÇÃO) | I74: PAN | K74: AG. ASS. DIG | L74: 45777 | N74: 42 | O74: 25-60 | P74: 411.3 | Q74: 397.71 | R74: 13300 | S74: 0 | T74: 13300 | W74: 0 | Y74: 0 | Z74: 4 | AA74: 2025 | AB74: 2025-04 | AC74: PORT
A75: 45776 | B75: 45783 | C75: DANIELE | D75: INSS | E75: 442.700.326-56 | F75: SÔNIA REGINA VIEIRA | G75: SF-100026 | H75: PORT (REDUÇÃO) | I75: PAN | K75: CANCELADO | L75: 45779 | N75: 60 | O75: 61-84 | P75: 248.72 | Q75: 333.7 | R75: 10500 | S75: 0 | T75: 10500 | W75: 0 | Y75: 0 | Z75: 4 | AA75: 2025 | AB75: 2025-04 | AC75: PORT
A76: 45778 | C76: PEDRO | D76: INSS | E76: 595.174.857-05 | F76: ALCIDES FERREIRA NETO | G76: SF-100027 | H76: REFIN DE PORT (REDUÇÃO) | I76: SAFRA | K76: CANCELADO | L76: 45781 | N76: 84 | O76: 61-84 | P76: 564.68 | Q76: 613.77 | R76: 0 | S76: 0 | T76: 0 | W76: 0 | Y76: 0 | Z76: 5 | AA76: 2025 | AB76: 2025-05 | AC76: REFIN DE PORT
A77: 45779 | C77: PEDRO | D77: INSS | E77: 814.164.199-14 | F77: NAIR DOS SANTOS BORGES | G77: SF-100028 | H77: PORT (REDUÇÃO) | I77: SAFRA | K77: CANCELADO | L77: 45782 | N77: 27 | O77: 25-60 | P77: 564.68 | Q77: 613.77 | R77: 13095.46 | S77: 0 | T77: 13095.46 | W77: 0 | Y77: 0 | Z77: 5 | AA77: 2025 | AB77: 2025-05 | AC77: PORT
A78: 45781 | C78: PEDRO | D78: INSS | E78: 889.757.507-77 | F78: JOSÉ DA SILVA SANTOS | G78: SF-100029 | H78: NOVO (REDUÇÃO) | I78: SAFRA | K78: CANCELADO | L78: 45784 | N78: 84 | O78: 61-84 | P78: 0 | Q78: 371.6 | R78: 0 | S78: 0 | T78: 0 | W78: 0 | Y78: 0 | Z78: 5 | AA78: 2025 | AB78: 2025-05 | AC78: NOVO
A79: 45783 | C79: DANIELE | D79: INSS | E79: 379.981.168-14 | F79: MARIA APARECIDA OLIVEIRA | G79: BR-100012 | H79: REFIN DE PORT (REDUÇÃO) | I79: SAFRA | K79: AG. ASS. DIG | L79: 45786 | N79: 84 | O79: 61-84 | P79: 101.1 | Q79: 103.27 | R79: 0 | S79: 0 | T79: 0 | W79: 0 | Y79: 0 | Z79: 5 | AA79: 2025 | AB79: 2025-05 | AC79: REFIN DE PORT
A80: 45784 | C80: DANIELE | D80: INSS | E80: 346.057.471-94 | F80: ANTÔNIO CARLOS PEREIRA | G80: BR-100013 | H80: PORT (REDUÇÃO) | I80: SAFRA | K80: AG. ASS. DIG | L80: 45787 | N80: 55 | O80: 25-60 | P80: 101.1 | Q80: 103.27 | R80: 4102.81 | S80: 0 | T80: 4102.81 | W80: 0 | Y80: 0 | Z80: 5 | AA80: 2025 | AB80: 2025-05 | AC80: PORT
A81: 45786 | C81: DANIELE | D81: INSS | E81: 181.372.091-69 | F81: FRANCISCA DE SOUZA LIMA | G81: PN-100037 | H81: REFIN DE PORT (REDUÇÃO) | I81: SAFRA | K81: AG. ASS. DIG | L81: 45789 | N81: 84 | O81: 61-84 | P81: 546.48 | Q81: 558.2 | R81: 0 | S81: 0 | T81: 0 | W81: 0 | Y81: 0 | Z81: 5 | AA81: 2025 | AB81: 2025-05 | AC81: REFIN DE PORT
A82: 45788 | C82: DANIELE | D82: INSS | E82: 360.047.834-19 | F82: JOÃO BATISTA FERREIRA | G82: PN-100038 | H82: PORT (REDUÇÃO) | I82: SAFRA | K82: AG. ASS. DIG | L82: 45791 | N82: 55 | O82: 25-60 | P82: 546.48 | Q82: 558.2 | R82: 22176.71 | S82: 0 | T82: 22176.71 | W82: 0 | Y82: 0 | Z82: 5 | AA82: 2025 | AB82: 2025-05 | AC82: PORT
A83: 45789 | B83: 45796 | C83: AMANDA | D83: INSS | E83: 635.575.794-63 | F83: ANA LÚCIA RODRIGUES | G83: PN-100039 | H83: REFIN DE PORT (REDUÇÃO) | I83: BRADESCO | K83: CANCELADO | L83: 45792 | N83: 84 | O83: 61-84 | P83: 435 | Q83: 757.47 | R83: 0 | S83: 0 | T83: 0 | W83: 0 | Y83: 0 | Z83: 5 | AA83: 2025 | AB83: 2025-05 | AC83: REFIN DE PORT
A84: 45791 | B84: 45798 | C84: AMANDA | D84: INSS | E84: 651.400.432-90 | F84: LUIZ CARLOS ALMEIDA | G84: PN-100040 | H84: PORT (REDUÇÃO) | I84: BRADESCO | K84: CANCELADO | L84: 45794 | N84: 38 | O84: 25-60 | P84: 756.32 | Q84: 757.47 | R84: 0 | S84: 0 | T84: 0 | W84: 0 | Y84: 0 | Z84: 5 | AA84: 2025 | AB84: 2025-05 | AC84: PORT
A85: 45793 | C85: ALEXANDRE | D85: INSS | E85: 335.511.472-45 | F85: CLAUDETE FERNANDES COSTA | G85: PN-100041 | H85: REFIN DE PORT (REDUÇÃO) | I85: PAN | K85: AG. ASS. DIG | L85: 45796 | N85: 84 | O85: 61-84 | P85: 230 | Q85: 312.82 | R85: 11600 | S85: 11355.39 | T85: 244.61 | W85: 0 | Y85: 0 | Z85: 5 | AA85: 2025 | AB85: 2025-05 | AC85: REFIN DE PORT
A86: 45794 | C86: ALEXANDRE | D86: INSS | E86: 124.258.428-97 | F86: SEBASTIÃO PEREIRA NUNES | G86: PN-100042 | H86: PORT (REDUÇÃO) | I86: PAN | K86: AG. ASS. DIG | L86: 45797 | N86: 61 | O86: 61-84 | P86: 270.6 | Q86: 312.82 | R86: 11355.39 | S86: 0 | T86: 11355.39 | W86: 0 | Y86: 0 | Z86: 5 | AA86: 2025 | AB86: 2025-05 | AC86: PORT
A87: 45796 | C87: AMANDA | D87: INSS | E87: 845.895.485-26 | F87: TEREZINHA DE JESUS RIBEIRO | G87: PN-100043 | H87: REFIN DE PORT (REDUÇÃO) | I87: PAN | K87: CANCELADO | L87: 45799 | N87: 32 | O87: 25-60 | P87: 295 | Q87: 587.21 | R87: 0 | S87: 14599.77 | T87: -14599.77 | W87: 0 | Y87: 0 | Z87: 5 | AA87: 2025 | AB87: 2025-05 | AC87: REFIN DE PORT
A88: 45798 | C88: AMANDA | D88: INSS | E88: 344.582.273-75 | F88: ADEMAR JOSÉ DOS SANTOS | G88: PN-100044 | H88: PORT (REDUÇÃO) | I88: PAN | K88: CANCELADO | L88: 45801 | N88: 32 | O88: 25-60 | P88: 560.99 | Q88: 587.21 | R88: 14599.77 | S88: 0 | T88: 14599.77 | W88: 0 | Y88: 0 | Z88: 5 | AA88: 2025 | AB88: 2025-05 | AC88: PORT
A89: 45799 | C89: AMANDA | D89: INSS | E89: 463.115.167-03 | F89: ROSA MARIA CARDOSO | G89: PN-100045 | H89: NOVO | I89: PAN | K89: CANCELADO | L89: 45802 | N89: 84 | O89: 61-84 | P89: 0 | Q89: 42.35 | R89: 1750.88 | S89: 0 | T89: 1750.88 | W89: 0 | Y89: 0 | Z89: 5 | AA89: 2025 | AB89: 2025-05 | AC89: NOVO
A90: 45801 | C90: AMANDA | D90: INSS | E90: 328.804.696-12 | F90: MANOEL FRANCISCO GOMES | G90: PN-100046 | H90: NOVO (REDUÇÃO) | I90: PAN | K90: CANCELADO | L90: 45804 | N90: 84 | O90: 61-84 | P90: 0 | Q90: 253.9 | R90: 10497.1 | S90: 0 | T90: 10497.1 | W90: 0 | Y90: 0 | Z90: 5 | AA90: 2025 | AB90: 2025-05 | AC90: NOVO
A91: 45803 | C91: AMANDA | D91: INSS | E91: 775.282.586-12 | F91: CONCEIÇÃO APARECIDA DIAS | G91: PN-100047 | H91: REFIN DE PORT (REDUÇÃO) | I91: PAN | K91: CANCELADO | L91: 45806 | N91: 84 | O91: 61-84 | P91: 235.45 | Q91: 489.35 | R91: 0 | S91: 0 | T91: 0 | W91: 0 | Y91: 0 | Z91: 5 | AA91: 2025 | AB91: 2025-05 | AC91: REFIN DE PORT
A92: 45804 | C92: AMANDA | D92: INSS | E92: 124.258.428-97 | F92: SEBASTIÃO PEREIRA NUNES | G92: PN-100048 | H92: PORT (REDUÇÃO) | I92: PAN | K92: CANCELADO | L92: 45807 | N92: 31 | O92: 25-60 | P92: 451.47 | Q92: 489.35 | R92: 11573.25 | S92: 0 | T92: 11573.25 | W92: 0 | Y92: 0 | Z92: 5 | AA92: 2025 | AB92: 2025-05 | AC92: PORT
A93: 45806 | C93: DANIELE | D93: INSS | E93: 836.292.520-15 | F93: DIRCE MARIA CAMPOS | G93: PN-100049 | H93: REFIN DE PORT (REDUÇÃO) | I93: PAN | K93: AG. ASS. DIG | L93: 45809 | N93: 84 | O93: 61-84 | P93: 282 | Q93: 640.76 | R93: 14374.98 | S93: 14093.16 | T93: 281.82 | W93: 0 | Y93: 0 | Z93: 5 | AA93: 2025 | AB93: 2025-05 | AC93: REFIN DE PORT
A94: 45808 | C94: DANIELE | D94: INSS | E94: 089.554.706-08 | F94: ALCIDES FERREIRA NETO | G94: PN-100050 | H94: PORT (REDUÇÃO) | I94: PAN | K94: AG. ASS. DIG | L94: 45811 | N94: 27 | O94: 25-60 | P94: 622.84 | Q94: 640.76 | R94: 14093.16 | S94: 0 | T94: 14093.16 | W94: 0 | Y94: 0 | Z94: 5 | AA94: 2025 | AB94: 2025-05 | AC94: PORT
A95: 45809 | C95: AMANDA | D95: INSS | E95: 811.025.517-81 | F95: HÉLIO PEREIRA DA CRUZ | G95: PN-100051 | H95: REFIN DE PORT (REDUÇÃO) | I95: PAN | K95: AG. ASS. DIG | L95: 45812 | N95: 84 | O95: 61-84 | P95: 243.96 | Q95: 465.89 | R95: 12300 | S95: 11900 | T95: 400 | W95: 0 | Y95: 0 | Z95: 6 | AA95: 2025 | AB95: 2025-06 | AC95: REFIN DE PORT
A96: 45811 | C96: AMANDA | D96: INSS | E96: 736.526.833-90 | F96: BENEDITO CARLOS ARAÚJO | G96: PN-100052 | H96: PORT (REDUÇÃO) | I96: PAN | K96: AG. ASS. DIG | L96: 45814 | N96: 31 | O96: 25-60 | P96: 464.21 | Q96: 465.89 | R96: 11900 | S96: 0 | T96: 11900 | W96: 0 | Y96: 0 | Z96: 6 | AA96: 2025 | AB96: 2025-06 | AC96: PORT
... A109: 45832 | C109: MARIA | D109: INSS | E109: 328.525.175-41 | F109: ZILDA APARECIDA FREITAS | G109: SF-100031 | H109: PORT (REDUÇÃO) | I109: PAN | K109: CANCELADO | L109: 45835 | N109: 57 | O109: 25-60 | P109: 150.05 | Q109: 166.3 | R109: 0 | S109: 0 | T109: 0 | W109: 0 | Y109: 0 | Z109: 6 | AA109: 2025 | AB109: 2025-06 | AC109: PORT
A110: 45834 | B110: 45841 | C110: AMANDA | D110: INSS | E110: 197.990.184-22 | F110: WALDEMAR PEREIRA SOBRINHO | G110: PN-100062 | H110: REFIN DE PORT (REDUÇÃO) | I110: BRADESCO | K110: CANCELADO | L110: 45837 | N110: 84 | O110: 61-84 | P110: 0 | Q110: 476.86 | R110: 0 | S110: 0 | T110: 0 | W110: 0 | Y110: 0 | Z110: 6 | AA110: 2025 | AB110: 2025-06 | AC110: REFIN DE PORT
A111: 45835 | B111: 45842 | C111: AMANDA | D111: INSS | E111: 736.526.833-90 | F111: BENEDITO CARLOS ARAÚJO | G111: PN-100063 | H111: PORT (REDUÇÃO) | I111: BRADESCO | K111: CANCELADO | L111: 45838 | N111: 0 | O111: <24 | P111: 0 | Q111: 476.86 | R111: 19819 | S111: 0 | T111: 19819 | W111: 0 | Y111: 0 | Z111: 6 | AA111: 2025 | AB111: 2025-06 | AC111: PORT
A112: 45837 | C112: AMANDA | D112: INSS | E112: 872.356.738-46 | F112: ANTÔNIO MARCOS RAMOS | G112: BR-100016 | H112: REFIN DE PORT (REDUÇÃO) | I112: SAFRA | K112: CANCELADO | L112: 45840 | N112: 84 | O112: 61-84 | P112: 441.33 | Q112: 568.04 | R112: 0 | S112: 0 | T112: 0 | W112: 0 | Y112: 0 | Z112: 6 | AA112: 2025 | AB112: 2025-06 | AC112: REFIN DE PORT
A113: 45839 | C113: AMANDA | D113: INSS | E113: 298.342.563-27 | F113: MARIA DAS GRAÇAS LEAL | G113: BR-100017 | H113: PORT (REDUÇÃO) | I113: SAFRA | K113: CANCELADO | L113: 45842 | N113: 58 | O113: 25-60 | P113: 562.2 | Q113: 568.04 | R113: 23707.43 | S113: 0 | T113: 23707.43 | W113: 0 | Y113: 0 | Z113: 7 | AA113: 2025 | AB113: 2025-07 | AC113: PORT
A114: 45840 | C114: DANIELE | D114: INSS | E114: 582.384.950-03 | F114: ORLANDO BATISTA NOGUEIRA | G114: BR-100018 | H114: REFIN DE PORT (REDUÇÃO) | I114: PAN | K114: CANCELADO | L114: 45843 | N114: 84 | O114: 61-84 | P114: 124 | Q114: 498.64 | R114: 0 | S114: 0 | T114: 0 | W114: 0 | Y114: 0 | Z114: 7 | AA114: 2025 | AB114: 2025-07 | AC114: REFIN DE PORT
A115: 45842 | C115: DANIELE | D115: INSS | E115: 360.047.834-19 | F115: JOÃO BATISTA FERREIRA | G115: BR-100019 | H115: PORT (REDUÇÃO) | I115: PAN | K115: CANCELADO | L115: 45845 | N115: 13 | O115: <24 | P115: 497.84 | Q115: 498.64 | R115: 5938.52 | S115: 0 | T115: 5938.52 | W115: 0 | Y115: 0 | Z115: 7 | AA115: 2025 | AB115: 2025-07 | AC115: PORT
A116: 45844 | B116: 45851 | C116: AMANDA | D116: INSS | E116: 742.601.274-99 | F116: WALTER LUIZ DE PAULA | G116: BR-100020 | H116: REFIN DE PORT (REDUÇÃO) | I116: BRADESCO | K116: CANCELADO | L116: 45847 | N116: 84 | O116: 61-84 | P116: 191.5 | Q116: 375.09 | R116: 0 | S116: 0 | T116: 0 | W116: 0 | Y116: 0 | Z116: 7 | AA116: 2025 | AB116: 2025-07 | AC116: REFIN DE PORT
A117: 45845 | B117: 45852 | C117: AMANDA | D117: INSS | E117: 302.318.852-37 | F117: IRENE FÁTIMA QUEIROZ | G117: BR-100021 | H117: PORT (REDUÇÃO) | I117: BRADESCO | K117: CANCELADO | L117: 45848 | N117: 32 | O117: 25-60 | P117: 373.56 | Q117: 375.09 | R117: 9800 | S117: 0 | T117: 9800 | W117: 0 | Y117: 0 | Z117: 7 | AA117: 2025 | AB117: 2025-07 | AC117: PORT
A118: 45847 | C118: AMANDA | D118: INSS | E118: 920.289.568-31 | F118: EDUARDO SANTANA FILHO | G118: BR-100022 | H118: NOVO (REDUÇÃO) | I118: BRADESCO | K118: DIGITAR | L118: 45850 | N118: 84 | O118: 61-84 | P118: 0 | Q118: 0 | R118: 0 | S118: 0 | T118: 0 | W118: 0 | Y118: 0 | Z118: 7 | AA118: 2025 | AB118: 2025-07 | AC118: NOVO
A119: 45849 | B119: 45856 | C119: MARIA | D119: INSS | E119: 105.304.772-76 | F119: HELENA MARIA BARROS | G119: PN-100064 | H119: PORT (REDUÇÃO) | I119: BRADESCO | K119: CANCELADO | L119: 45852 | N119: 72 | O119: 61-84 | P119: 60.09 | Q119: 95.37 | R119: 2850 | S119: 0 | T119: 2850 | W119: 0 | Y119: 0 | Z119: 7 | AA119: 2025 | AB119: 2025-07 | AC119: PORT
A120: 45850 | B120: 45857 | C120: AMANDA | D120: INSS | E120: 591.568.765-43 | F120: IVONE DA CONCEIÇÃO MELO | G120: PN-100065 | H120: REFIN DE PORT (REDUÇÃO) | I120: BRADESCO | K120: EM ANÁLISE | L120: 45853 | N120: 84 | O120: 61-84 | P120: 211 | Q120: 299.3 | R120: 11142.43 | S120: 10837.52 | T120: 304.91 | W120: 0 | Y120: 0 | Z120: 7 | AA120: 2025 | AB120: 2025-07 | AC120: REFIN DE PORT
A121: 45852 | B121: 45859 | C121: AMANDA | D121: INSS | E121: 746.514.957-41 | F121: SUELI APARECIDA PRADO | G121: PN-100066 | H121: PORT (REDUÇÃO) | I121: BRADESCO | K121: SALDO PAGO | L121: 45855 | N121: 56 | O121: 25-60 | P121: 267.55 | Q121: 299.3 | R121: 10837.52 | S121: 0 | T121: 10837.52 | W121: 0 | X121: 45862 | Y121: 1 | Z121: 7 | AA121: 2025 | AB121: 2025-07 | AC121: PORT
A122: 45854 | C122: ANA JULIA | D122: INSS | E122: 134.926.533-42 | F122: MÁRIO ROBERTO MAGALHÃES | G122: BR-100023 | H122: PORT (REDUÇÃO) | I122: BRADESCO | K122: PENDENTE | L122: 45857 | N122: 58 | O122: 25-60 | P122: 844.71 | Q122: 993.81 | R122: 0 | S122: 0 | T122: 0 | W122: 0 | Y122: 0 | Z122: 7 | AA122: 2025 | AB122: 2025-07 | AC122: PORT
A123: 45855 | C123: AMANDA | D123: INSS | E123: 992.757.262-97 | F123: CLEUSA MARIA DA SILVA | G123: BR-100024 | H123: REFIN DE PORT (REDUÇÃO) | I123: PAN | K123: CANCELADO | L123: 45858 | N123: 84 | O123: 61-84 | P123: 201 | Q123: 375.09 | R123: 0 | S123: 0 | T123: 0 | W123: 0 | Y123: 0 | Z123: 7 | AA123: 2025 | AB123: 2025-07 | AC123: REFIN DE PORT
...

Sheet dCalendario
A1: Data | B1: Ano | C1: Mês | D1: Número do Mês | E1: Nome do Mês
A2: 45658 | B2: 2025 | C2: 1 | D2: 1 | E2: janeiro
A3: 45659 | B3: 2025 | C3: 1 | D3: 1 | E3: janeiro
A4: 45661 | B4: 2025 | C4: 1 | D4: 1 | E4: janeiro
A5: 45663 | B5: 2025 | C5: 1 | D5: 1 | E5: janeiro
A6: 45664 | B6: 2025 | C6: 1 | D6: 1 | E6: janeiro
A7: 45666 | B7: 2025 | C7: 1 | D7: 1 | E7: janeiro
A8: 45668 | B8: 2025 | C8: 1 | D8: 1 | E8: janeiro
A9: 45669 | B9: 2025 | C9: 1 | D9: 1 | E9: janeiro
A10: 45671 | B10: 2025 | C10: 1 | D10: 1 | E10: janeiro
A11: 45673 | B11: 2025 | C11: 1 | D11: 1 | E11: janeiro
A12: 45674 | B12: 2025 | C12: 1 | D12: 1 | E12: janeiro
A13: 45676 | B13: 2025 | C13: 1 | D13: 1 | E13: janeiro
... A223: 46021 | B223: 2025 | C223: 12 | D223: 12 | E223: dezembro

Sheet dOperador
A1: Operadores
A2: AMANDA
A3: PEDRO
A4: ALEXANDRE
A5: MARIA
A6: ANA JULIA
A7: DANIELE
A8: CLAUDIO
